boa_zksync/IContractDeployer.json
boa_zksync/__init__.py
boa_zksync/browser.py
boa_zksync/compile.py
boa_zksync/compiler_utils.py
boa_zksync/contract.py
boa_zksync/deployer.py
boa_zksync/environment.py
boa_zksync/node.py
boa_zksync/types.py
boa_zksync/util.py
boa_zksync/verifiers.py
titanoboa_zksync-0.2.10.dist-info/licenses/LICENSE
titanoboa_zksync-0.2.10.dist-info/METADATA
titanoboa_zksync-0.2.10.dist-info/WHEEL
titanoboa_zksync-0.2.10.dist-info/top_level.txt
titanoboa_zksync-0.2.10.dist-info/RECORD
