Metadata-Version: 2.4
Name: titanoboa-zksync
Version: 0.2.10
Summary: A Zksync plugin for the Titanoboa Vyper interpreter
License: MIT License
Keywords: ethereum,evm,smart contract,development,vyper,zksync
Classifier: Topic :: Software Development
License-File: LICENSE
Requires-Dist: titanoboa>=0.2.6
Provides-Extra: forking-recommended
Requires-Dist: ujson; extra == "forking-recommended"
Dynamic: license-file
